setup.py
dsnd_gb_distributions/Binomialdistribution.py
dsnd_gb_distributions/Gaussiandistribution.py
dsnd_gb_distributions/Generaldistribution.py
dsnd_gb_distributions/__init__.py
dsnd_gb_distributions.egg-info/PKG-INFO
dsnd_gb_distributions.egg-info/SOURCES.txt
dsnd_gb_distributions.egg-info/dependency_links.txt
dsnd_gb_distributions.egg-info/not-zip-safe
dsnd_gb_distributions.egg-info/top_level.txt