Metadata-Version: 1.0
Name: dsnd-gb-distributions
Version: 1.0
Summary: Gaussian and Binomial distributions
Home-page: UNKNOWN
Author: Bruno Guimarães de Oliveira
Author-email: oliveira.ufrj11@gmail.com
License: UNKNOWN
Platform: UNKNOWN
